tempera/__init__.py
tempera/examples.py
tempera/temperature.py
tempera-1.0.1.dist-info/LICENSE.txt
tempera-1.0.1.dist-info/METADATA
tempera-1.0.1.dist-info/WHEEL
tempera-1.0.1.dist-info/top_level.txt
tempera-1.0.1.dist-info/RECORD
