Metadata-Version: 2.1
Name: tempera
Version: 1.0.1
Summary: Convert and return temperature objects in set global scale.
Home-page: https://github.com/Hyperdimensionals/tempera
Author: Brendan Krueger
Author-email: atleasticanbe@gmail.com
License: UNKNOWN
Project-URL: Source, https://github.com/Hyperdimensionals/tempera
Project-URL: Donate, https://www.paypal.com/donate?hosted_button_id=3C7CBND5MJ5RE
Keywords: temperature conversion celsius fahrenheit kelvin centigrade climate control
Platform: UNKNOWN
Classifier: Programming Language :: Python :: 3
Classifier: License :: OSI Approved :: MIT License
Classifier: Operating System :: OS Independent
